{
  "metadata": {
    "purpose": "Complete phrase structures for B2 essay body paragraphs and conclusions",
    "audience": "B2 students",
    "description": "Topic sentences, transitions, and concluding statements",
    "version": "1.0"
  },
  "structures": {
    "for_and_against": {
      "title": "For & Against Essays - Body & Conclusion",
      "sections": {
        "advantages": {
          "label": "Body Paragraph - Advantages",
          "purpose": "Introduce advantage points",
          "phrases": {
            "default": [
              "One clear advantage of [topic] is that it...",
              "A major benefit is that [topic] enables people to...",
              "Another positive aspect is that [topic] can help to...",
              "A further strength of [topic] is that it...",
              "One important benefit is that [topic] allows..."
            ],
            "alt1": [
              "The main advantage of [topic] is that it...",
              "One major benefit of [topic] is that it...",
              "A key positive point is that [topic]...",
              "Another advantage worth noting is that [topic]...",
              "[Topic] also has the benefit of..."
            ],
            "alt2": [
              "A significant benefit of [topic] is that it...",
              "Another strong point is that [topic] helps to...",
              "One clear advantage lies in the fact that [topic]...",
              "From a practical standpoint, [topic] enables...",
              "An additional benefit is that [topic] tends to..."
            ]
          }
        },
        "transition_to_disadvantages": {
          "label": "Transition - Moving to Disadvantages",
          "purpose": "Shift from positives to negatives smoothly",
          "phrases": {
            "default": [
              "However, there are also some downsides to consider.",
              "That said, [topic] is not without problems.",
              "On the other hand, some people point out that...",
              "Even so, there are drawbacks that should not be ignored.",
              "Despite these benefits, [topic] may still cause difficulties."
            ],
            "alt1": [
              "Nevertheless, [topic] does have certain disadvantages.",
              "It is important to note, however, that [topic] also has negative aspects.",
              "While these advantages are significant, we must also consider...",
              "Turning to the drawbacks, it is clear that...",
              "A more critical view reveals that..."
            ],
            "alt2": [
              "Having examined the benefits, we must now look at the costs.",
              "Set against these advantages are several concerns.",
              "The picture is not entirely positive, however.",
              "A balanced discussion requires us to acknowledge that...",
              "These benefits must be weighed against..."
            ]
          }
        },
        "disadvantages": {
          "label": "Body Paragraph - Disadvantages",
          "purpose": "Introduce disadvantage points",
          "phrases": {
            "default": [
              "One disadvantage of [topic] is that it...",
              "A common issue is that [topic] can lead to...",
              "Another concern is that [topic] may...",
              "A further problem with [topic] is that it...",
              "One clear drawback is that [topic] tends to..."
            ],
            "alt1": [
              "The key disadvantage of [topic] is that it...",
              "A major drawback of [topic] is that it...",
              "Another negative aspect is that [topic]...",
              "One serious limitation of [topic] is that it...",
              "[Topic] also has the downside of..."
            ],
            "alt2": [
              "A significant downside of [topic] is that it...",
              "One notable problem is that [topic]...",
              "Another criticism is that [topic] can...",
              "A clear disadvantage lies in the fact that [topic]...",
              "From a critical perspective, [topic] tends to..."
            ]
          }
        },
        "conclusion": {
          "label": "Conclusion",
          "purpose": "Summarise both sides and give a balanced final view",
          "phrases": {
            "default": [
              "To sum up, [topic] has both advantages and disadvantages.",
              "Overall, I believe the benefits of [topic] outweigh the drawbacks.",
              "All in all, whether [topic] is positive depends on [condition].",
              "On balance, [topic] can be useful if managed properly.",
              "In conclusion, a sensible approach is to maximize the benefits while minimizing the risks."
            ],
            "alt1": [
              "In conclusion, [topic] presents both opportunities and challenges.",
              "Having considered both sides, it seems that the advantages are more significant.",
              "Weighing up the evidence, [topic] appears to be beneficial overall.",
              "The key is to harness the benefits of [topic] while addressing its drawbacks.",
              "Ultimately, [topic] can be positive if appropriate safeguards are in place."
            ],
            "alt2": [
              "Taking everything into account, [topic] offers more benefits than problems.",
              "A balanced view suggests that [topic] is worthwhile despite its limitations.",
              "While [topic] is not perfect, its advantages make it valuable.",
              "The evidence indicates that [topic] can be beneficial when used responsibly.",
              "In the final analysis, the case for [topic] is stronger than the case against it."
            ]
          }
        }
      }
    },
    "problems_and_solutions": {
      "title": "Problems & Solutions - Body & Conclusion",
      "sections": {
        "problems": {
          "label": "Body Paragraph - Problems",
          "purpose": "Introduce problem points",
          "phrases": {
            "default": [
              "One major problem is that...",
              "A serious issue is that...",
              "Another significant difficulty is that...",
              "A key challenge is that...",
              "One pressing concern is that..."
            ],
            "alt1": [
              "The main problem with [topic] is that...",
              "A critical issue is that...",
              "Another worrying aspect is that...",
              "One fundamental difficulty is that...",
              "A major obstacle is that..."
            ],
            "alt2": [
              "Perhaps the most serious problem is that...",
              "A particularly troubling issue is that...",
              "Another significant challenge facing [group] is that...",
              "One of the key difficulties is that...",
              "A persistent problem is that..."
            ]
          }
        },
        "transition_to_solutions": {
          "label": "Transition - Moving to Solutions",
          "purpose": "Signal that solutions are coming",
          "phrases": {
            "default": [
              "Fortunately, there are several ways to deal with this.",
              "There are practical steps that could improve the situation.",
              "Despite these difficulties, solutions do exist.",
              "Even small changes could make a difference.",
              "With the right approach, the impact of [problem] can be reduced."
            ],
            "alt1": [
              "However, these problems are not insurmountable.",
              "A range of measures could be introduced to tackle these challenges.",
              "There are effective strategies that could address [problem].",
              "The good news is that workable solutions are available.",
              "By taking action, we can significantly reduce [problem]."
            ],
            "alt2": [
              "Turning now to possible solutions, several approaches show promise.",
              "Having identified the problems, we can now consider how to resolve them.",
              "Rather than accepting the situation, we can implement targeted strategies.",
              "Action at multiple levels could help to overcome these challenges.",
              "While the problems are serious, they can be addressed through..."
            ]
          }
        },
        "solutions": {
          "label": "Body Paragraph - Solutions",
          "purpose": "Introduce solution points",
          "phrases": {
            "default": [
              "One possible solution would be to...",
              "A practical approach is to...",
              "Another effective measure would be to...",
              "Governments/Schools/Companies could help by...",
              "An important step would be to..."
            ],
            "alt1": [
              "The most effective solution would be to...",
              "A promising approach is to...",
              "Another way to address this is to...",
              "Authorities could introduce policies that...",
              "A key measure would be to..."
            ],
            "alt2": [
              "Perhaps the best way forward is to...",
              "A workable solution involves...",
              "Another strategy worth considering is to...",
              "One practical step would be to...",
              "A comprehensive approach would include..."
            ]
          }
        },
        "conclusion": {
          "label": "Conclusion",
          "purpose": "Summarise and end with a realistic final message",
          "phrases": {
            "default": [
              "In conclusion, [problem] is serious, but it can be reduced with the right action.",
              "To sum up, a combination of different measures would improve the situation.",
              "Overall, if these steps are taken, [positive result] is likely.",
              "In the end, shared responsibility is key to solving [problem].",
              "With consistent effort, real progress can be made."
            ],
            "alt1": [
              "In conclusion, while [problem] poses challenges, effective solutions exist.",
              "Taking everything into account, [problem] can be addressed through coordinated action.",
              "The key to success is implementing these measures consistently.",
              "Ultimately, tackling [problem] requires both prevention and practical support.",
              "With commitment from all stakeholders, [problem] can be significantly reduced."
            ],
            "alt2": [
              "In the final analysis, [problem] is manageable if we act decisively.",
              "A coordinated response combining these approaches offers the best hope.",
              "While no single solution is perfect, together these measures can make a real difference.",
              "The evidence suggests that with sustained effort, [problem] can be overcome.",
              "In the long run, investing in these solutions will benefit [society/group] greatly."
            ]
          }
        }
      }
    },
    "cause_and_effect": {
      "title": "Cause & Effect - Body & Conclusion",
      "sections": {
        "causes": {
          "label": "Body Paragraph - Causes",
          "purpose": "Introduce cause points",
          "phrases": {
            "default": [
              "One key cause of [phenomenon] is...",
              "A major reason for [phenomenon] is...",
              "Another important factor is...",
              "A significant cause is...",
              "One primary reason is..."
            ],
            "alt1": [
              "The main cause of [phenomenon] is...",
              "A critical factor contributing to [phenomenon] is...",
              "Another driving force behind [phenomenon] is...",
              "One fundamental reason for [phenomenon] is...",
              "A key factor that has led to [phenomenon] is..."
            ],
            "alt2": [
              "Perhaps the most significant cause of [phenomenon] is...",
              "At the root of [phenomenon] lies...",
              "Another major contributor to [phenomenon] is...",
              "One essential factor explaining [phenomenon] is...",
              "A crucial element in the rise of [phenomenon] is..."
            ]
          }
        },
        "transition_to_effects": {
          "label": "Transition - Moving to Effects",
          "purpose": "Shift from causes to consequences",
          "phrases": {
            "default": [
              "Because of these reasons, [phenomenon] has several effects.",
              "This situation leads to a number of consequences.",
              "As a result, we can see changes in...",
              "These factors have had an impact on...",
              "Consequently, [group/area] has been affected."
            ],
            "alt1": [
              "Having examined the causes, we can now turn to the effects.",
              "These driving forces have produced significant consequences.",
              "The outcomes of [phenomenon] are evident in several ways.",
              "Moving from causes to consequences, it is clear that...",
              "The effects of [phenomenon] can be observed across [area]."
            ],
            "alt2": [
              "The causal factors outlined above have led to important changes.",
              "As a direct result of these causes, we now see...",
              "The consequences of [phenomenon] are both wide-ranging and significant.",
              "Having identified why [phenomenon] occurs, we must now consider what it produces.",
              "These causes have set in motion a series of effects."
            ]
          }
        },
        "effects": {
          "label": "Body Paragraph - Effects",
          "purpose": "Introduce effect points",
          "phrases": {
            "default": [
              "One major effect of [phenomenon] is that...",
              "A significant consequence is that...",
              "Another important result is that...",
              "A key impact is that...",
              "One notable outcome is that..."
            ],
            "alt1": [
              "The main effect of [phenomenon] is that...",
              "A critical consequence is that...",
              "Another substantial result is that...",
              "One fundamental impact is that...",
              "A primary outcome is that..."
            ],
            "alt2": [
              "Perhaps the most significant effect is that...",
              "The most visible consequence is that...",
              "Another far-reaching result is that...",
              "One particularly important impact is that...",
              "A major outcome affecting [group] is that..."
            ]
          }
        },
        "conclusion": {
          "label": "Conclusion",
          "purpose": "Summarise the relationship between causes and effects",
          "phrases": {
            "default": [
              "To sum up, [phenomenon] is caused by several factors and has noticeable effects.",
              "Overall, understanding the causes helps us deal with the consequences more effectively.",
              "In conclusion, [phenomenon] is a complex issue with both clear reasons and real impacts.",
              "All in all, the causes and effects are closely connected.",
              "For these reasons, it is important to address the causes, not just the results."
            ],
            "alt1": [
              "In conclusion, [phenomenon] emerges from multiple causes and produces significant effects.",
              "The analysis shows clear links between the origins and outcomes of [phenomenon].",
              "Understanding both causes and effects is essential for addressing [phenomenon].",
              "Taking everything into account, [phenomenon] represents a complex causal relationship.",
              "Ultimately, effective responses must target the root causes rather than merely treating symptoms."
            ],
            "alt2": [
              "In the final analysis, [phenomenon] results from interconnected causes and generates wide-ranging effects.",
              "The causal chain from origins to outcomes reveals the complexity of [phenomenon].",
              "By tracing causes to their effects, we gain insight into how [phenomenon] shapes [area].",
              "Both the drivers and the consequences of [phenomenon] warrant serious attention.",
              "A comprehensive understanding requires recognizing that causes and effects form a continuous cycle."
            ]
          }
        }
      }
    },
    "agree_and_disagree": {
      "title": "Agree & Disagree - Body & Conclusion",
      "sections": {
        "arguments_agree": {
          "label": "Body Paragraph - Reasons to Agree",
          "purpose": "Introduce arguments supporting the statement",
          "phrases": {
            "default": [
              "Those who agree often argue that...",
              "One reason to support this view is that...",
              "A key argument in favor is that...",
              "Supporters of this position claim that...",
              "Another point supporting [statement] is that..."
            ],
            "alt1": [
              "The main argument for [statement] is that...",
              "Advocates of this view emphasize that...",
              "One compelling reason to agree is that...",
              "Those who defend this position point out that...",
              "A further justification for [statement] is that..."
            ],
            "alt2": [
              "From the perspective of supporters, [statement] makes sense because...",
              "The strongest argument in favor is that...",
              "Proponents of this view highlight that...",
              "One persuasive reason to accept [statement] is that...",
              "Another consideration supporting this position is that..."
            ]
          }
        },
        "transition_to_disagree": {
          "label": "Transition - Moving to Opposing View",
          "purpose": "Shift to the opposing side smoothly",
          "phrases": {
            "default": [
              "However, there are also strong arguments against this idea.",
              "On the other hand, many people believe that...",
              "That said, it is worth considering the opposite viewpoint.",
              "Nevertheless, not everyone would accept this argument.",
              "Despite these points, critics claim that..."
            ],
            "alt1": [
              "Turning to the opposing view, critics argue that...",
              "A different perspective challenges these arguments.",
              "However, the other side of this debate presents compelling objections.",
              "It is important to acknowledge, however, that many dispute this view.",
              "A more skeptical position highlights flaws in this reasoning."
            ],
            "alt2": [
              "Having considered the case for [statement], we must now examine the case against it.",
              "Contrasting sharply with this view, opponents contend that...",
              "The arguments above are not without serious challenges.",
              "A critical perspective reveals important weaknesses in this position.",
              "Balance requires us to hear from those who fundamentally disagree."
            ]
          }
        },
        "arguments_disagree": {
          "label": "Body Paragraph - Reasons to Disagree",
          "purpose": "Introduce arguments opposing the statement",
          "phrases": {
            "default": [
              "Those who disagree point out that...",
              "A strong counter-argument is that...",
              "One reason to oppose this view is that...",
              "Critics of this position argue that...",
              "Another point against [statement] is that..."
            ],
            "alt1": [
              "The main argument against [statement] is that...",
              "Opponents of this view emphasize that...",
              "One compelling reason to disagree is that...",
              "Those who reject this position highlight that...",
              "A further objection to [statement] is that..."
            ],
            "alt2": [
              "From the perspective of critics, [statement] is flawed because...",
              "The strongest argument against this view is that...",
              "Skeptics of this position point out that...",
              "One persuasive reason to reject [statement] is that...",
              "Another consideration undermining this position is that..."
            ]
          }
        },
        "personal_opinion": {
          "label": "Body Paragraph - Your Opinion",
          "purpose": "State and justify your own position",
          "phrases": {
            "default": [
              "In my opinion, I (agree/disagree) because...",
              "Personally, I believe that [position] mainly because...",
              "From my point of view, the strongest argument is...",
              "Having considered both sides, I think that...",
              "My own view is that..."
            ],
            "alt1": [
              "Having weighed the arguments, I am convinced that...",
              "On balance, I find the case for [position] more persuasive because...",
              "After careful consideration, my position is that...",
              "I am inclined to [agree/disagree] for the following reasons...",
              "The evidence leads me to conclude that..."
            ],
            "alt2": [
              "Taking everything into account, I believe [position] because...",
              "The preponderance of evidence supports [position].",
              "While I respect the opposing view, I ultimately side with [position] because...",
              "A fair assessment of both sides leads me to [position].",
              "My considered judgment is that [statement] is [valid/invalid] because..."
            ]
          }
        },
        "conclusion": {
          "label": "Conclusion",
          "purpose": "Summarise and restate your position",
          "phrases": {
            "default": [
              "To sum up, while both sides make valid points, I believe that...",
              "Overall, I maintain that [statement] is [true/false] because...",
              "In conclusion, after considering both perspectives, my view is that...",
              "All in all, the arguments suggest that...",
              "For these reasons, I remain convinced that..."
            ],
            "alt1": [
              "In conclusion, having examined the debate thoroughly, I stand by [position].",
              "The balance of evidence favors [position].",
              "Weighing the arguments carefully, I conclude that...",
              "While the opposing view has merit, the stronger case is for...",
              "Ultimately, the most defensible position is that..."
            ],
            "alt2": [
              "In the final analysis, [position] represents the most reasonable conclusion.",
              "A balanced assessment leads inescapably to [position].",
              "The weight of argument falls decisively on the side of [position].",
              "Taking all factors into consideration, [statement] is best viewed as [valid/invalid].",
              "The preponderance of evidence, logic, and practical considerations supports [position]."
            ]
          }
        }
      }
    },
    "opinion": {
      "title": "Opinion Essay - Body & Conclusion",
      "sections": {
        "argument_1": {
          "label": "Body Paragraph - First Reason",
          "purpose": "Introduce your strongest argument",
          "phrases": {
            "default": [
              "Firstly, one key reason is that...",
              "The main reason for my view is that...",
              "My primary argument is that...",
              "The most important point is that...",
              "To begin with, [opinion] is justified because..."
            ],
            "alt1": [
              "First and foremost, [opinion] is right because...",
              "The central argument supporting my position is that...",
              "My strongest reason for believing this is that...",
              "The foundation of my view rests on...",
              "At the heart of my position is the fact that..."
            ],
            "alt2": [
              "The most compelling reason for [opinion] is that...",
              "My primary justification is that...",
              "The cornerstone of my argument is that...",
              "Above all, [opinion] is warranted because...",
              "The principal basis for my view is that..."
            ]
          }
        },
        "argument_2": {
          "label": "Body Paragraph - Second Reason",
          "purpose": "Introduce your second strongest argument",
          "phrases": {
            "default": [
              "Secondly, another important point is that...",
              "In addition, [opinion] is supported by...",
              "A further reason for my view is that...",
              "Moreover, [topic] demonstrates that...",
              "Another key argument is that..."
            ],
            "alt1": [
              "Furthermore, [opinion] makes sense because...",
              "An additional consideration is that...",
              "My second main reason is that...",
              "Building on this, it is also true that...",
              "Equally important is the fact that..."
            ],
            "alt2": [
              "Beyond this, [opinion] is justified by...",
              "A complementary argument is that...",
              "Reinforcing this position is the observation that...",
              "Another substantial reason is that...",
              "Supporting this view further is the fact that..."
            ]
          }
        },
        "counter_argument": {
          "label": "Body Paragraph - Counter-argument (Optional)",
          "purpose": "Acknowledge and address opposing views",
          "phrases": {
            "default": [
              "Some people might argue that...",
              "It is true that... However, I believe that...",
              "Although there are some concerns, I still think that...",
              "Critics may claim that... but...",
              "Admittedly, there are situations where... Nevertheless..."
            ],
            "alt1": [
              "While it could be argued that... this overlooks...",
              "Opponents may suggest that... yet this fails to consider...",
              "It must be acknowledged that... However, this does not undermine...",
              "Some would contend that... but this objection is not decisive because...",
              "A potential criticism is that... This concern, however, can be addressed by..."
            ],
            "alt2": [
              "A skeptic might object that... This objection, though understandable, is not compelling because...",
              "Critics point to... as a weakness, but careful analysis shows...",
              "While respecting opposing views, I find them unconvincing because...",
              "The counter-argument that... does not withstand scrutiny since...",
              "Alternative perspectives exist, but they fail to account for..."
            ]
          }
        },
        "conclusion": {
          "label": "Conclusion",
          "purpose": "Restate your opinion and summarize",
          "phrases": {
            "default": [
              "In conclusion, I believe that [opinion].",
              "To sum up, my view is that [opinion].",
              "Overall, the reasons above support the position that [opinion].",
              "All in all, I remain convinced that [opinion].",
              "For these reasons, I would strongly support [opinion]."
            ],
            "alt1": [
              "In conclusion, I stand by my position that [opinion].",
              "Taking everything into consideration, [opinion] is the right approach.",
              "The evidence clearly supports [opinion].",
              "Having examined the issue thoroughly, I maintain that [opinion].",
              "Ultimately, [opinion] represents the most sensible view."
            ],
            "alt2": [
              "In the final analysis, [opinion] is fully justified.",
              "The cumulative force of these arguments establishes that [opinion].",
              "A fair assessment leads inevitably to [opinion].",
              "All considerations point toward [opinion].",
              "The weight of argument decisively supports [opinion]."
            ]
          }
        }
      }
    },
    "speculation_and_trends": {
      "title": "Trends & Predictions - Body & Conclusion",
      "sections": {
        "causes": {
          "label": "Body Paragraph - Causes of Trend",
          "purpose": "Introduce cause points for the trend",
          "phrases": {
            "default": [
              "One main reason for [trend] is that...",
              "This trend is largely due to...",
              "A key factor driving [trend] is...",
              "An important cause of [trend] is...",
              "One primary reason people are [action] is..."
            ],
            "alt1": [
              "The principal driver of [trend] is...",
              "[Trend] can be attributed mainly to...",
              "A significant factor behind [trend] is...",
              "The main catalyst for this shift is...",
              "At the root of [trend] is..."
            ],
            "alt2": [
              "The fundamental force propelling [trend] is...",
              "[Trend] stems primarily from...",
              "A critical determinant of [trend] is...",
              "The underlying impetus for [trend] is...",
              "The genesis of [trend] can be traced to..."
            ]
          }
        },
        "transition_to_future": {
          "label": "Transition - Moving to Predictions",
          "purpose": "Shift from causes to predictions",
          "phrases": {
            "default": [
              "Looking ahead, this trend is likely to continue.",
              "If this pattern persists, we can expect...",
              "In the future, [trend] will probably...",
              "Based on current patterns, it is reasonable to predict that...",
              "Turning to the future, [trend] is expected to..."
            ],
            "alt1": [
              "Projecting forward, [trend] shows no signs of slowing.",
              "The future trajectory of [trend] suggests that...",
              "As we look to the coming years, [trend] will likely...",
              "Extrapolating from present conditions, we can anticipate...",
              "The outlook for [trend] indicates that..."
            ],
            "alt2": [
              "Having examined the causes, we can now speculate about outcomes.",
              "The logical extension of current developments is that...",
              "If present dynamics continue, the probable result is...",
              "Forecasting based on established patterns, we can expect...",
              "The future evolution of [trend] will likely be characterized by..."
            ]
          }
        },
        "predictions": {
          "label": "Body Paragraph - Predictions",
          "purpose": "Introduce prediction points about the future",
          "phrases": {
            "default": [
              "It is likely that [trend] will become more widespread.",
              "In the future, [trend] will probably...",
              "[Trend] is expected to...",
              "We can anticipate that [trend] will...",
              "It seems probable that [trend] will..."
            ],
            "alt1": [
              "[Trend] is likely to intensify in the coming years.",
              "The future will probably see [trend] becoming...",
              "Current indicators suggest that [trend] will...",
              "There is a strong likelihood that [trend] will...",
              "Projections indicate that [trend] will..."
            ],
            "alt2": [
              "The trajectory points toward [trend] becoming...",
              "In all probability, [trend] will...",
              "The most plausible scenario is that [trend] will...",
              "Barring unforeseen changes, [trend] will...",
              "The weight of evidence suggests [trend] will..."
            ]
          }
        },
        "conclusion": {
          "label": "Conclusion",
          "purpose": "Summarize the trend, causes, and predictions",
          "phrases": {
            "default": [
              "To sum up, [trend] is growing because of [causes], and it will probably continue.",
              "Overall, this trend is likely to shape [area] in the future.",
              "In conclusion, [trend] seems set to grow, although its effects will depend on [condition].",
              "All in all, the future of [trend] looks significant.",
              "On balance, this trend will bring both opportunities and challenges."
            ],
            "alt1": [
              "In conclusion, [trend] represents a significant shift with a promising/concerning future.",
              "The analysis suggests [trend] will persist and intensify.",
              "Taking everything into account, [trend] is poised for continued growth.",
              "Ultimately, [trend] will likely become a defining feature of [area].",
              "The trajectory of [trend] points toward substantial future impact."
            ],
            "alt2": [
              "In the final analysis, [trend] constitutes a transformative force with far-reaching implications.",
              "The synthesis of causes and projections indicates [trend] will reshape [area] fundamentally.",
              "A comprehensive view suggests [trend] will prove to be one of the defining developments of our time.",
              "The convergence of factors ensures [trend] will accelerate and deepen.",
              "Future historians will likely view [trend] as a watershed moment in [area]."
            ]
          }
        }
      }
    }
  }
}
